lmu/__init__.py
lmu/version.py
lmu/tests/__init__.py
lmu/tests/test_lmu.py
lmu-0.4.0.dist-info/LICENSE.rst
lmu-0.4.0.dist-info/METADATA
lmu-0.4.0.dist-info/WHEEL
lmu-0.4.0.dist-info/top_level.txt
lmu-0.4.0.dist-info/RECORD
