Metadata-Version: 2.1
Name: lmu
Version: 0.4.0
Summary: LMU metapackage for installing various LMU implementations
Home-page: https://github.com/nengo/lmu
Author: Applied Brain Research
Author-email: info@appliedbrainresearch.com
License: Free for non-commercial use
Platform: UNKNOWN
Classifier: Development Status :: 3 - Alpha
Classifier: Intended Audience :: Science/Research
Classifier: License :: Free for non-commercial use
Classifier: Operating System :: OS Independent
Classifier: Programming Language :: Python 
Classifier: Programming Language :: Python :: 3.6
Classifier: Programming Language :: Python :: 3.7
Classifier: Programming Language :: Python :: 3.8
Classifier: Topic :: Scientific/Engineering 
Classifier: Topic :: Scientific/Engineering :: Artificial Intelligence
Requires-Python: >=3.6
License-File: LICENSE.rst
Requires-Dist: keras-lmu (>=0.4.0)
Provides-Extra: all
Requires-Dist: pytest (>=6.1.0) ; extra == 'all'
Provides-Extra: docs
Provides-Extra: optional
Provides-Extra: tests
Requires-Dist: pytest (>=6.1.0) ; extra == 'tests'
